synalinks/__init__.py
synalinks/api/__init__.py
synalinks/api/backend/__init__.py
synalinks/api/callbacks/__init__.py
synalinks/api/callbacks/monitor/__init__.py
synalinks/api/config/__init__.py
synalinks/api/datasets/__init__.py
synalinks/api/datasets/arcagi/__init__.py
synalinks/api/datasets/gsm8k/__init__.py
synalinks/api/datasets/hotpotqa/__init__.py
synalinks/api/embedding_models/__init__.py
synalinks/api/hooks/__init__.py
synalinks/api/initializers/__init__.py
synalinks/api/language_models/__init__.py
synalinks/api/metrics/__init__.py
synalinks/api/modules/__init__.py
synalinks/api/ops/__init__.py
synalinks/api/ops/embedding_models/__init__.py
synalinks/api/ops/json/__init__.py
synalinks/api/ops/knowledge_bases/__init__.py
synalinks/api/optimizers/__init__.py
synalinks/api/programs/__init__.py
synalinks/api/rewards/__init__.py
synalinks/api/saving/__init__.py
synalinks/api/tree/__init__.py
synalinks/api/utils/__init__.py
synalinks/src/__init__.py
synalinks/src/api_export.py
synalinks/src/version.py
synalinks/src/backend/__init__.py
synalinks/src/backend/config.py
synalinks/src/backend/common/__init__.py
synalinks/src/backend/common/dynamic_json_schema_utils.py
synalinks/src/backend/common/dynamic_json_schema_utils_test.py
synalinks/src/backend/common/global_state.py
synalinks/src/backend/common/global_state_test.py
synalinks/src/backend/common/json_data_model.py
synalinks/src/backend/common/json_data_model_test.py
synalinks/src/backend/common/json_schema_utils.py
synalinks/src/backend/common/json_schema_utils_test.py
synalinks/src/backend/common/json_utils.py
synalinks/src/backend/common/json_utils_test.py
synalinks/src/backend/common/name_scope.py
synalinks/src/backend/common/name_scope_test.py
synalinks/src/backend/common/numpy.py
synalinks/src/backend/common/stateless_scope.py
synalinks/src/backend/common/symbolic_data_model.py
synalinks/src/backend/common/symbolic_data_model_test.py
synalinks/src/backend/common/symbolic_scope.py
synalinks-0.6.11.dist-info/licenses/LICENSE
synalinks-0.6.11.dist-info/METADATA
synalinks-0.6.11.dist-info/WHEEL
synalinks-0.6.11.dist-info/top_level.txt
synalinks-0.6.11.dist-info/RECORD
